odoo8_addon_sale_order_line_date-8.0.1.0.0-py2.7-nspkg.pth
odoo8_addon_sale_order_line_date-8.0.1.0.0.dist-info/DESCRIPTION.rst
odoo8_addon_sale_order_line_date-8.0.1.0.0.dist-info/METADATA
odoo8_addon_sale_order_line_date-8.0.1.0.0.dist-info/RECORD
odoo8_addon_sale_order_line_date-8.0.1.0.0.dist-info/WHEEL
odoo8_addon_sale_order_line_date-8.0.1.0.0.dist-info/metadata.json
odoo8_addon_sale_order_line_date-8.0.1.0.0.dist-info/namespace_packages.txt
odoo8_addon_sale_order_line_date-8.0.1.0.0.dist-info/top_level.txt
odoo_addons/sale_order_line_date/README.rst
odoo_addons/sale_order_line_date/__init__.py
odoo_addons/sale_order_line_date/__openerp__.py
odoo_addons/sale_order_line_date/i18n/es.po
odoo_addons/sale_order_line_date/i18n/pt_BR.po
odoo_addons/sale_order_line_date/i18n/ro.po
odoo_addons/sale_order_line_date/i18n/sl.po
odoo_addons/sale_order_line_date/models/__init__.py
odoo_addons/sale_order_line_date/models/sale_order.py
odoo_addons/sale_order_line_date/tests/__init__.py
odoo_addons/sale_order_line_date/tests/test_sale_order_line_date.py
odoo_addons/sale_order_line_date/views/sale_order_view.xml
