Metadata-Version: 2.0
Name: odoo8-addon-sale-order-line-date
Version: 8.0.1.0.0
Summary: Sale Order Line Date
Home-page: https://github.com/OCA/sale-workflow/
Author: OdooMRP team,AvanzOSC,Serv. Tecnol. Avanzados - Pedro M. Baeza,Odoo Community Association (OCA)
Author-email: support@odoo-community.org
License: AGPL-3
Platform: UNKNOWN
Classifier: Programming Language :: Python :: 2.7
Classifier: Framework :: Odoo
Classifier: License :: OSI Approved :: GNU Affero General Public License v3
Requires-Dist: odoo (<9.0a,>=8.0a)
